p13r0n_rmillionaires/__init__.py
p13r0n_rmillionaires/lifelines.py
p13r0n_rmillionaires-0.4.dist-info/LICENCE.txt
p13r0n_rmillionaires-0.4.dist-info/METADATA
p13r0n_rmillionaires-0.4.dist-info/WHEEL
p13r0n_rmillionaires-0.4.dist-info/top_level.txt
p13r0n_rmillionaires-0.4.dist-info/RECORD
