Metadata-Version: 2.1
Name: p13r0n_rmillionaires
Version: 0.4
Summary: Lifeline fuctions package necessary to run Rock Millionaires
Author-email: ppieron <piotrek.pieron@gmail.com>
License: MIT License
Project-URL: Homepage, https://github.com/ppieron/Millionaires_Rock.git
Keywords: Rock Millionaires
Classifier: Programming Language :: Python
Classifier: Topic :: Education
Classifier: Topic :: Games/Entertainment
Requires-Python: >=3.0
License-File: LICENCE.txt
